sleekxmppfs/__init__.py
sleekxmppfs/api.py
sleekxmppfs/basexmpp.py
sleekxmppfs/clientxmpp.py
sleekxmppfs/componentxmpp.py
sleekxmppfs/exceptions.py
sleekxmppfs/jid.py
sleekxmppfs/version.py
sleekxmppfs/features/__init__.py
sleekxmppfs/features/feature_bind/__init__.py
sleekxmppfs/features/feature_bind/bind.py
sleekxmppfs/features/feature_bind/stanza.py
sleekxmppfs/features/feature_mechanisms/__init__.py
sleekxmppfs/features/feature_mechanisms/mechanisms.py
sleekxmppfs/features/feature_mechanisms/stanza/__init__.py
sleekxmppfs/features/feature_mechanisms/stanza/abort.py
sleekxmppfs/features/feature_mechanisms/stanza/auth.py
sleekxmppfs/features/feature_mechanisms/stanza/challenge.py
sleekxmppfs/features/feature_mechanisms/stanza/failure.py
sleekxmppfs/features/feature_mechanisms/stanza/mechanisms.py
sleekxmppfs/features/feature_mechanisms/stanza/response.py
sleekxmppfs/features/feature_mechanisms/stanza/success.py
sleekxmppfs/features/feature_preapproval/__init__.py
sleekxmppfs/features/feature_preapproval/preapproval.py
sleekxmppfs/features/feature_preapproval/stanza.py
sleekxmppfs/features/feature_rosterver/__init__.py
sleekxmppfs/features/feature_rosterver/rosterver.py
sleekxmppfs/features/feature_rosterver/stanza.py
sleekxmppfs/features/feature_session/__init__.py
sleekxmppfs/features/feature_session/session.py
sleekxmppfs/features/feature_session/stanza.py
sleekxmppfs/features/feature_starttls/__init__.py
sleekxmppfs/features/feature_starttls/stanza.py
sleekxmppfs/features/feature_starttls/starttls.py
sleekxmppfs/plugins/__init__.py
sleekxmppfs/plugins/base.py
sleekxmppfs/plugins/gmail_notify.py
sleekxmppfs/plugins/xep_0045.py
sleekxmppfs/plugins/xep_0082.py
sleekxmppfs/plugins/xep_0106.py
sleekxmppfs/plugins/xep_0133.py
sleekxmppfs/plugins/xep_0138.py
sleekxmppfs/plugins/xep_0163.py
sleekxmppfs/plugins/xep_0222.py
sleekxmppfs/plugins/xep_0223.py
sleekxmppfs/plugins/xep_0242.py
sleekxmppfs/plugins/xep_0256.py
sleekxmppfs/plugins/xep_0270.py
sleekxmppfs-1.4.1.dist-info/LICENSE
sleekxmppfs-1.4.1.dist-info/METADATA
sleekxmppfs-1.4.1.dist-info/WHEEL
sleekxmppfs-1.4.1.dist-info/top_level.txt
sleekxmppfs-1.4.1.dist-info/RECORD
