Metadata-Version: 2.1
Name: sleekxmppfs
Version: 1.4.1
Summary: A fork of SleekXMPP with TLS cert validation disabled, intended only to be used with the sucks project
Home-page: http://github.com/aszymanik/SleekXMPP
Author: Alex Szymanik
Author-email: aszymanik@gmail.com
License: MIT
Platform: any
Classifier: Intended Audience :: Developers
Classifier: License :: OSI Approved :: MIT License
Classifier: Programming Language :: Python
Classifier: Programming Language :: Python :: 2.7
Classifier: Programming Language :: Python :: 3.4
Classifier: Programming Language :: Python :: 3.5
Classifier: Programming Language :: Python :: 3.6
Classifier: Topic :: Software Development :: Libraries :: Python Modules
Requires: dnspython
Requires: pyasn1
Requires: pyasn1_modules
License-File: LICENSE
